[{"name":"cursor_particle_features","qualifiedName":"cursor_particle_features","href":"features_cursor_particle_features/features_cursor_particle_features-library.html","type":"library","overriddenDepth":0,"packageName":"dart_board_particles"},{"name":"CursorFeature","qualifiedName":"cursor_particle_features.CursorFeature","href":"features_cursor_particle_features/CursorFeature-class.html","type":"class","overriddenDepth":0,"packageName":"dart_board_particles","enclosedBy":{"name":"cursor_particle_features","type":"library"}},{"name":"CursorFeature","qualifiedName":"cursor_particle_features.CursorFeature.CursorFeature","href":"features_cursor_particle_features/CursorFeature/CursorFeature.html","type":"constructor","overriddenDepth":0,"packageName":"dart_board_particles","enclosedBy":{"name":"CursorFeature","type":"class"}},{"name":"appDecorations","qualifiedName":"cursor_particle_features.CursorFeature.appDecorations","href":"features_cursor_particle_features/CursorFeature/appDecorations.html","type":"property","overriddenDepth":0,"packageName":"dart_board_particles","enclosedBy":{"name":"CursorFeature","type":"class"}},{"name":"dependencies","qualifiedName":"cursor_particle_features.CursorFeature.dependencies","href":"features_cursor_particle_features/CursorFeature/dependencies.html","type":"property","overriddenDepth":0,"packageName":"dart_board_particles","enclosedBy":{"name":"CursorFeature","type":"class"}},{"name":"enabled","qualifiedName":"cursor_particle_features.CursorFeature.enabled","href":"features_cursor_particle_features/CursorFeature/enabled.html","type":"property","overriddenDepth":0,"packageName":"dart_board_particles","enclosedBy":{"name":"CursorFeature","type":"class"}},{"name":"generateParticleLayer","qualifiedName":"cursor_particle_features.CursorFeature.generateParticleLayer","href":"features_cursor_particle_features/CursorFeature/generateParticleLayer.html","type":"method","overriddenDepth":0,"packageName":"dart_board_particles","enclosedBy":{"name":"CursorFeature","type":"class"}},{"name":"implementationName","qualifiedName":"cursor_particle_features.CursorFeature.implementationName","href":"features_cursor_particle_features/CursorFeature/implementationName.html","type":"property","overriddenDepth":0,"packageName":"dart_board_particles","enclosedBy":{"name":"CursorFeature","type":"class"}},{"name":"namespace","qualifiedName":"cursor_particle_features.CursorFeature.namespace","href":"features_cursor_particle_features/CursorFeature/namespace.html","type":"property","overriddenDepth":0,"packageName":"dart_board_particles","enclosedBy":{"name":"CursorFeature","type":"class"}},{"name":"pageDecorationAllowList","qualifiedName":"cursor_particle_features.CursorFeature.pageDecorationAllowList","href":"features_cursor_particle_features/CursorFeature/pageDecorationAllowList.html","type":"property","overriddenDepth":0,"packageName":"dart_board_particles","enclosedBy":{"name":"CursorFeature","type":"class"}},{"name":"pageDecorationDenyList","qualifiedName":"cursor_particle_features.CursorFeature.pageDecorationDenyList","href":"features_cursor_particle_features/CursorFeature/pageDecorationDenyList.html","type":"property","overriddenDepth":0,"packageName":"dart_board_particles","enclosedBy":{"name":"CursorFeature","type":"class"}},{"name":"pageDecorations","qualifiedName":"cursor_particle_features.CursorFeature.pageDecorations","href":"features_cursor_particle_features/CursorFeature/pageDecorations.html","type":"property","overriddenDepth":0,"packageName":"dart_board_particles","enclosedBy":{"name":"CursorFeature","type":"class"}},{"name":"routes","qualifiedName":"cursor_particle_features.CursorFeature.routes","href":"features_cursor_particle_features/CursorFeature/routes.html","type":"property","overriddenDepth":0,"packageName":"dart_board_particles","enclosedBy":{"name":"CursorFeature","type":"class"}},{"name":"toString","qualifiedName":"cursor_particle_features.CursorFeature.toString","href":"features_cursor_particle_features/CursorFeature/toString.html","type":"method","overriddenDepth":1,"packageName":"dart_board_particles","enclosedBy":{"name":"CursorFeature","type":"class"}},{"name":"FireCursorFeature","qualifiedName":"cursor_particle_features.FireCursorFeature","href":"features_cursor_particle_features/FireCursorFeature-class.html","type":"class","overriddenDepth":0,"packageName":"dart_board_particles","enclosedBy":{"name":"cursor_particle_features","type":"library"}},{"name":"FireCursorFeature","qualifiedName":"cursor_particle_features.FireCursorFeature.FireCursorFeature","href":"features_cursor_particle_features/FireCursorFeature/FireCursorFeature.html","type":"constructor","overriddenDepth":0,"packageName":"dart_board_particles","enclosedBy":{"name":"FireCursorFeature","type":"class"}},{"name":"generateParticleLayer","qualifiedName":"cursor_particle_features.FireCursorFeature.generateParticleLayer","href":"features_cursor_particle_features/FireCursorFeature/generateParticleLayer.html","type":"method","overriddenDepth":1,"packageName":"dart_board_particles","enclosedBy":{"name":"FireCursorFeature","type":"class"}},{"name":"namespace","qualifiedName":"cursor_particle_features.FireCursorFeature.namespace","href":"features_cursor_particle_features/FireCursorFeature/namespace.html","type":"property","overriddenDepth":0,"packageName":"dart_board_particles","enclosedBy":{"name":"FireCursorFeature","type":"class"}},{"name":"RainbowCursorFeature","qualifiedName":"cursor_particle_features.RainbowCursorFeature","href":"features_cursor_particle_features/RainbowCursorFeature-class.html","type":"class","overriddenDepth":0,"packageName":"dart_board_particles","enclosedBy":{"name":"cursor_particle_features","type":"library"}},{"name":"RainbowCursorFeature","qualifiedName":"cursor_particle_features.RainbowCursorFeature.RainbowCursorFeature","href":"features_cursor_particle_features/RainbowCursorFeature/RainbowCursorFeature.html","type":"constructor","overriddenDepth":0,"packageName":"dart_board_particles","enclosedBy":{"name":"RainbowCursorFeature","type":"class"}},{"name":"generateParticleLayer","qualifiedName":"cursor_particle_features.RainbowCursorFeature.generateParticleLayer","href":"features_cursor_particle_features/RainbowCursorFeature/generateParticleLayer.html","type":"method","overriddenDepth":1,"packageName":"dart_board_particles","enclosedBy":{"name":"RainbowCursorFeature","type":"class"}},{"name":"namespace","qualifiedName":"cursor_particle_features.RainbowCursorFeature.namespace","href":"features_cursor_particle_features/RainbowCursorFeature/namespace.html","type":"property","overriddenDepth":0,"packageName":"dart_board_particles","enclosedBy":{"name":"RainbowCursorFeature","type":"class"}},{"name":"oldX","qualifiedName":"cursor_particle_features.RainbowCursorFeature.oldX","href":"features_cursor_particle_features/RainbowCursorFeature/oldX.html","type":"property","overriddenDepth":0,"packageName":"dart_board_particles","enclosedBy":{"name":"RainbowCursorFeature","type":"class"}},{"name":"oldY","qualifiedName":"cursor_particle_features.RainbowCursorFeature.oldY","href":"features_cursor_particle_features/RainbowCursorFeature/oldY.html","type":"property","overriddenDepth":0,"packageName":"dart_board_particles","enclosedBy":{"name":"RainbowCursorFeature","type":"class"}},{"name":"dart_board_particle_feature","qualifiedName":"dart_board_particle_feature","href":"dart_board_particle_feature/dart_board_particle_feature-library.html","type":"library","overriddenDepth":0,"packageName":"dart_board_particles"},{"name":"BackgroundPainter","qualifiedName":"dart_board_particle_feature.BackgroundPainter","href":"dart_board_particle_feature/BackgroundPainter.html","type":"typedef","overriddenDepth":0,"packageName":"dart_board_particles","enclosedBy":{"name":"dart_board_particle_feature","type":"library"}},{"name":"DartBoardParticleDecoration","qualifiedName":"dart_board_particle_feature.DartBoardParticleDecoration","href":"dart_board_particle_feature/DartBoardParticleDecoration-class.html","type":"class","overriddenDepth":0,"packageName":"dart_board_particles","enclosedBy":{"name":"dart_board_particle_feature","type":"library"}},{"name":"DartBoardParticleDecoration","qualifiedName":"dart_board_particle_feature.DartBoardParticleDecoration.DartBoardParticleDecoration","href":"dart_board_particle_feature/DartBoardParticleDecoration/DartBoardParticleDecoration.html","type":"constructor","overriddenDepth":0,"packageName":"dart_board_particles","enclosedBy":{"name":"DartBoardParticleDecoration","type":"class"}},{"name":"child","qualifiedName":"dart_board_particle_feature.DartBoardParticleDecoration.child","href":"dart_board_particle_feature/DartBoardParticleDecoration/child.html","type":"property","overriddenDepth":0,"packageName":"dart_board_particles","enclosedBy":{"name":"DartBoardParticleDecoration","type":"class"}},{"name":"createState","qualifiedName":"dart_board_particle_feature.DartBoardParticleDecoration.createState","href":"dart_board_particle_feature/DartBoardParticleDecoration/createState.html","type":"method","overriddenDepth":1,"packageName":"dart_board_particles","enclosedBy":{"name":"DartBoardParticleDecoration","type":"class"}},{"name":"interface","qualifiedName":"dart_board_particle_feature.DartBoardParticleDecoration.interface","href":"dart_board_particle_feature/DartBoardParticleDecoration/interface.html","type":"property","overriddenDepth":0,"packageName":"dart_board_particles","enclosedBy":{"name":"DartBoardParticleDecoration","type":"class"}},{"name":"DartBoardParticleFeature","qualifiedName":"dart_board_particle_feature.DartBoardParticleFeature","href":"dart_board_particle_feature/DartBoardParticleFeature-class.html","type":"class","overriddenDepth":0,"packageName":"dart_board_particles","enclosedBy":{"name":"dart_board_particle_feature","type":"library"}},{"name":"DartBoardParticleFeature","qualifiedName":"dart_board_particle_feature.DartBoardParticleFeature.DartBoardParticleFeature","href":"dart_board_particle_feature/DartBoardParticleFeature/DartBoardParticleFeature.html","type":"constructor","overriddenDepth":0,"packageName":"dart_board_particles","enclosedBy":{"name":"DartBoardParticleFeature","type":"class"}},{"name":"appDecorations","qualifiedName":"dart_board_particle_feature.DartBoardParticleFeature.appDecorations","href":"dart_board_particle_feature/DartBoardParticleFeature/appDecorations.html","type":"property","overriddenDepth":0,"packageName":"dart_board_particles","enclosedBy":{"name":"DartBoardParticleFeature","type":"class"}},{"name":"dependencies","qualifiedName":"dart_board_particle_feature.DartBoardParticleFeature.dependencies","href":"dart_board_particle_feature/DartBoardParticleFeature/dependencies.html","type":"property","overriddenDepth":0,"packageName":"dart_board_particles","enclosedBy":{"name":"DartBoardParticleFeature","type":"class"}},{"name":"enabled","qualifiedName":"dart_board_particle_feature.DartBoardParticleFeature.enabled","href":"dart_board_particle_feature/DartBoardParticleFeature/enabled.html","type":"property","overriddenDepth":0,"packageName":"dart_board_particles","enclosedBy":{"name":"DartBoardParticleFeature","type":"class"}},{"name":"implementationName","qualifiedName":"dart_board_particle_feature.DartBoardParticleFeature.implementationName","href":"dart_board_particle_feature/DartBoardParticleFeature/implementationName.html","type":"property","overriddenDepth":0,"packageName":"dart_board_particles","enclosedBy":{"name":"DartBoardParticleFeature","type":"class"}},{"name":"namespace","qualifiedName":"dart_board_particle_feature.DartBoardParticleFeature.namespace","href":"dart_board_particle_feature/DartBoardParticleFeature/namespace.html","type":"property","overriddenDepth":0,"packageName":"dart_board_particles","enclosedBy":{"name":"DartBoardParticleFeature","type":"class"}},{"name":"pageDecorationAllowList","qualifiedName":"dart_board_particle_feature.DartBoardParticleFeature.pageDecorationAllowList","href":"dart_board_particle_feature/DartBoardParticleFeature/pageDecorationAllowList.html","type":"property","overriddenDepth":0,"packageName":"dart_board_particles","enclosedBy":{"name":"DartBoardParticleFeature","type":"class"}},{"name":"pageDecorationDenyList","qualifiedName":"dart_board_particle_feature.DartBoardParticleFeature.pageDecorationDenyList","href":"dart_board_particle_feature/DartBoardParticleFeature/pageDecorationDenyList.html","type":"property","overriddenDepth":0,"packageName":"dart_board_particles","enclosedBy":{"name":"DartBoardParticleFeature","type":"class"}},{"name":"pageDecorations","qualifiedName":"dart_board_particle_feature.DartBoardParticleFeature.pageDecorations","href":"dart_board_particle_feature/DartBoardParticleFeature/pageDecorations.html","type":"property","overriddenDepth":0,"packageName":"dart_board_particles","enclosedBy":{"name":"DartBoardParticleFeature","type":"class"}},{"name":"routes","qualifiedName":"dart_board_particle_feature.DartBoardParticleFeature.routes","href":"dart_board_particle_feature/DartBoardParticleFeature/routes.html","type":"property","overriddenDepth":0,"packageName":"dart_board_particles","enclosedBy":{"name":"DartBoardParticleFeature","type":"class"}},{"name":"toString","qualifiedName":"dart_board_particle_feature.DartBoardParticleFeature.toString","href":"dart_board_particle_feature/DartBoardParticleFeature/toString.html","type":"method","overriddenDepth":1,"packageName":"dart_board_particles","enclosedBy":{"name":"DartBoardParticleFeature","type":"class"}},{"name":"Particle","qualifiedName":"dart_board_particle_feature.Particle","href":"dart_board_particle_feature/Particle-class.html","type":"class","overriddenDepth":0,"packageName":"dart_board_particles","enclosedBy":{"name":"dart_board_particle_feature","type":"library"}},{"name":"Particle","qualifiedName":"dart_board_particle_feature.Particle.Particle","href":"dart_board_particle_feature/Particle/Particle.html","type":"constructor","overriddenDepth":0,"packageName":"dart_board_particles","enclosedBy":{"name":"Particle","type":"class"}},{"name":"step","qualifiedName":"dart_board_particle_feature.Particle.step","href":"dart_board_particle_feature/Particle/step.html","type":"method","overriddenDepth":0,"packageName":"dart_board_particles","enclosedBy":{"name":"Particle","type":"class"}},{"name":"ParticleLayer","qualifiedName":"dart_board_particle_feature.ParticleLayer","href":"dart_board_particle_feature/ParticleLayer-class.html","type":"class","overriddenDepth":0,"packageName":"dart_board_particles","enclosedBy":{"name":"dart_board_particle_feature","type":"library"}},{"name":"ParticleLayer","qualifiedName":"dart_board_particle_feature.ParticleLayer.ParticleLayer","href":"dart_board_particle_feature/ParticleLayer/ParticleLayer.html","type":"constructor","overriddenDepth":0,"packageName":"dart_board_particles","enclosedBy":{"name":"ParticleLayer","type":"class"}},{"name":"after","qualifiedName":"dart_board_particle_feature.ParticleLayer.after","href":"dart_board_particle_feature/ParticleLayer/after.html","type":"method","overriddenDepth":0,"packageName":"dart_board_particles","enclosedBy":{"name":"ParticleLayer","type":"class"}},{"name":"before","qualifiedName":"dart_board_particle_feature.ParticleLayer.before","href":"dart_board_particle_feature/ParticleLayer/before.html","type":"method","overriddenDepth":0,"packageName":"dart_board_particles","enclosedBy":{"name":"ParticleLayer","type":"class"}},{"name":"drawParticle","qualifiedName":"dart_board_particle_feature.ParticleLayer.drawParticle","href":"dart_board_particle_feature/ParticleLayer/drawParticle.html","type":"method","overriddenDepth":0,"packageName":"dart_board_particles","enclosedBy":{"name":"ParticleLayer","type":"class"}},{"name":"isDead","qualifiedName":"dart_board_particle_feature.ParticleLayer.isDead","href":"dart_board_particle_feature/ParticleLayer/isDead.html","type":"property","overriddenDepth":0,"packageName":"dart_board_particles","enclosedBy":{"name":"ParticleLayer","type":"class"}},{"name":"needsAfter","qualifiedName":"dart_board_particle_feature.ParticleLayer.needsAfter","href":"dart_board_particle_feature/ParticleLayer/needsAfter.html","type":"property","overriddenDepth":0,"packageName":"dart_board_particles","enclosedBy":{"name":"ParticleLayer","type":"class"}},{"name":"needsBefore","qualifiedName":"dart_board_particle_feature.ParticleLayer.needsBefore","href":"dart_board_particle_feature/ParticleLayer/needsBefore.html","type":"property","overriddenDepth":0,"packageName":"dart_board_particles","enclosedBy":{"name":"ParticleLayer","type":"class"}},{"name":"needsParticlePaint","qualifiedName":"dart_board_particle_feature.ParticleLayer.needsParticlePaint","href":"dart_board_particle_feature/ParticleLayer/needsParticlePaint.html","type":"property","overriddenDepth":0,"packageName":"dart_board_particles","enclosedBy":{"name":"ParticleLayer","type":"class"}},{"name":"particles","qualifiedName":"dart_board_particle_feature.ParticleLayer.particles","href":"dart_board_particle_feature/ParticleLayer/particles.html","type":"property","overriddenDepth":0,"packageName":"dart_board_particles","enclosedBy":{"name":"ParticleLayer","type":"class"}},{"name":"step","qualifiedName":"dart_board_particle_feature.ParticleLayer.step","href":"dart_board_particle_feature/ParticleLayer/step.html","type":"method","overriddenDepth":0,"packageName":"dart_board_particles","enclosedBy":{"name":"ParticleLayer","type":"class"}},{"name":"time","qualifiedName":"dart_board_particle_feature.ParticleLayer.time","href":"dart_board_particle_feature/ParticleLayer/time.html","type":"property","overriddenDepth":0,"packageName":"dart_board_particles","enclosedBy":{"name":"ParticleLayer","type":"class"}},{"name":"ParticlePainter","qualifiedName":"dart_board_particle_feature.ParticlePainter","href":"dart_board_particle_feature/ParticlePainter-class.html","type":"class","overriddenDepth":0,"packageName":"dart_board_particles","enclosedBy":{"name":"dart_board_particle_feature","type":"library"}},{"name":"ParticlePainter","qualifiedName":"dart_board_particle_feature.ParticlePainter.ParticlePainter","href":"dart_board_particle_feature/ParticlePainter/ParticlePainter.html","type":"constructor","overriddenDepth":0,"packageName":"dart_board_particles","enclosedBy":{"name":"ParticlePainter","type":"class"}},{"name":"interface","qualifiedName":"dart_board_particle_feature.ParticlePainter.interface","href":"dart_board_particle_feature/ParticlePainter/interface.html","type":"property","overriddenDepth":0,"packageName":"dart_board_particles","enclosedBy":{"name":"ParticlePainter","type":"class"}},{"name":"paint","qualifiedName":"dart_board_particle_feature.ParticlePainter.paint","href":"dart_board_particle_feature/ParticlePainter/paint.html","type":"method","overriddenDepth":1,"packageName":"dart_board_particles","enclosedBy":{"name":"ParticlePainter","type":"class"}},{"name":"shouldRepaint","qualifiedName":"dart_board_particle_feature.ParticlePainter.shouldRepaint","href":"dart_board_particle_feature/ParticlePainter/shouldRepaint.html","type":"method","overriddenDepth":1,"packageName":"dart_board_particles","enclosedBy":{"name":"ParticlePainter","type":"class"}},{"name":"Particles","qualifiedName":"dart_board_particle_feature.Particles","href":"dart_board_particle_feature/Particles-class.html","type":"class","overriddenDepth":0,"packageName":"dart_board_particles","enclosedBy":{"name":"dart_board_particle_feature","type":"library"}},{"name":"Particles","qualifiedName":"dart_board_particle_feature.Particles.Particles","href":"dart_board_particle_feature/Particles/Particles.html","type":"constructor","overriddenDepth":0,"packageName":"dart_board_particles","enclosedBy":{"name":"Particles","type":"class"}},{"name":"addLayer","qualifiedName":"dart_board_particle_feature.Particles.addLayer","href":"dart_board_particle_feature/Particles/addLayer.html","type":"method","overriddenDepth":0,"packageName":"dart_board_particles","enclosedBy":{"name":"Particles","type":"class"}},{"name":"instance","qualifiedName":"dart_board_particle_feature.Particles.instance","href":"dart_board_particle_feature/Particles/instance.html","type":"property","overriddenDepth":0,"packageName":"dart_board_particles","enclosedBy":{"name":"Particles","type":"class"}},{"name":"removeLayer","qualifiedName":"dart_board_particle_feature.Particles.removeLayer","href":"dart_board_particle_feature/Particles/removeLayer.html","type":"method","overriddenDepth":0,"packageName":"dart_board_particles","enclosedBy":{"name":"Particles","type":"class"}},{"name":"lastFrame","qualifiedName":"dart_board_particle_feature.lastFrame","href":"dart_board_particle_feature/lastFrame.html","type":"top-level property","overriddenDepth":0,"packageName":"dart_board_particles","enclosedBy":{"name":"dart_board_particle_feature","type":"library"}},{"name":"fire_particle","qualifiedName":"fire_particle","href":"presets_fire_particle/presets_fire_particle-library.html","type":"library","overriddenDepth":0,"packageName":"dart_board_particles"},{"name":"FireParticle","qualifiedName":"fire_particle.FireParticle","href":"presets_fire_particle/FireParticle-class.html","type":"class","overriddenDepth":0,"packageName":"dart_board_particles","enclosedBy":{"name":"fire_particle","type":"library"}},{"name":"FireParticle","qualifiedName":"fire_particle.FireParticle.FireParticle","href":"presets_fire_particle/FireParticle/FireParticle.html","type":"constructor","overriddenDepth":0,"packageName":"dart_board_particles","enclosedBy":{"name":"FireParticle","type":"class"}},{"name":"c","qualifiedName":"fire_particle.FireParticle.c","href":"presets_fire_particle/FireParticle/c.html","type":"property","overriddenDepth":0,"packageName":"dart_board_particles","enclosedBy":{"name":"FireParticle","type":"class"}},{"name":"m","qualifiedName":"fire_particle.FireParticle.m","href":"presets_fire_particle/FireParticle/m.html","type":"property","overriddenDepth":0,"packageName":"dart_board_particles","enclosedBy":{"name":"FireParticle","type":"class"}},{"name":"r","qualifiedName":"fire_particle.FireParticle.r","href":"presets_fire_particle/FireParticle/r.html","type":"property","overriddenDepth":0,"packageName":"dart_board_particles","enclosedBy":{"name":"FireParticle","type":"class"}},{"name":"r2","qualifiedName":"fire_particle.FireParticle.r2","href":"presets_fire_particle/FireParticle/r2.html","type":"property","overriddenDepth":0,"packageName":"dart_board_particles","enclosedBy":{"name":"FireParticle","type":"class"}},{"name":"r3","qualifiedName":"fire_particle.FireParticle.r3","href":"presets_fire_particle/FireParticle/r3.html","type":"property","overriddenDepth":0,"packageName":"dart_board_particles","enclosedBy":{"name":"FireParticle","type":"class"}},{"name":"s","qualifiedName":"fire_particle.FireParticle.s","href":"presets_fire_particle/FireParticle/s.html","type":"property","overriddenDepth":0,"packageName":"dart_board_particles","enclosedBy":{"name":"FireParticle","type":"class"}},{"name":"step","qualifiedName":"fire_particle.FireParticle.step","href":"presets_fire_particle/FireParticle/step.html","type":"method","overriddenDepth":1,"packageName":"dart_board_particles","enclosedBy":{"name":"FireParticle","type":"class"}},{"name":"t","qualifiedName":"fire_particle.FireParticle.t","href":"presets_fire_particle/FireParticle/t.html","type":"property","overriddenDepth":0,"packageName":"dart_board_particles","enclosedBy":{"name":"FireParticle","type":"class"}},{"name":"x","qualifiedName":"fire_particle.FireParticle.x","href":"presets_fire_particle/FireParticle/x.html","type":"property","overriddenDepth":0,"packageName":"dart_board_particles","enclosedBy":{"name":"FireParticle","type":"class"}},{"name":"y","qualifiedName":"fire_particle.FireParticle.y","href":"presets_fire_particle/FireParticle/y.html","type":"property","overriddenDepth":0,"packageName":"dart_board_particles","enclosedBy":{"name":"FireParticle","type":"class"}},{"name":"FireParticleLayer","qualifiedName":"fire_particle.FireParticleLayer","href":"presets_fire_particle/FireParticleLayer-class.html","type":"class","overriddenDepth":0,"packageName":"dart_board_particles","enclosedBy":{"name":"fire_particle","type":"library"}},{"name":"FireParticleLayer","qualifiedName":"fire_particle.FireParticleLayer.FireParticleLayer","href":"presets_fire_particle/FireParticleLayer/FireParticleLayer.html","type":"constructor","overriddenDepth":0,"packageName":"dart_board_particles","enclosedBy":{"name":"FireParticleLayer","type":"class"}},{"name":"after","qualifiedName":"fire_particle.FireParticleLayer.after","href":"presets_fire_particle/FireParticleLayer/after.html","type":"method","overriddenDepth":1,"packageName":"dart_board_particles","enclosedBy":{"name":"FireParticleLayer","type":"class"}},{"name":"before","qualifiedName":"fire_particle.FireParticleLayer.before","href":"presets_fire_particle/FireParticleLayer/before.html","type":"method","overriddenDepth":1,"packageName":"dart_board_particles","enclosedBy":{"name":"FireParticleLayer","type":"class"}},{"name":"drawParticle","qualifiedName":"fire_particle.FireParticleLayer.drawParticle","href":"presets_fire_particle/FireParticleLayer/drawParticle.html","type":"method","overriddenDepth":1,"packageName":"dart_board_particles","enclosedBy":{"name":"FireParticleLayer","type":"class"}},{"name":"isDead","qualifiedName":"fire_particle.FireParticleLayer.isDead","href":"presets_fire_particle/FireParticleLayer/isDead.html","type":"property","overriddenDepth":0,"packageName":"dart_board_particles","enclosedBy":{"name":"FireParticleLayer","type":"class"}},{"name":"particles","qualifiedName":"fire_particle.FireParticleLayer.particles","href":"presets_fire_particle/FireParticleLayer/particles.html","type":"property","overriddenDepth":0,"packageName":"dart_board_particles","enclosedBy":{"name":"FireParticleLayer","type":"class"}},{"name":"screenX","qualifiedName":"fire_particle.FireParticleLayer.screenX","href":"presets_fire_particle/FireParticleLayer/screenX.html","type":"property","overriddenDepth":0,"packageName":"dart_board_particles","enclosedBy":{"name":"FireParticleLayer","type":"class"}},{"name":"screenY","qualifiedName":"fire_particle.FireParticleLayer.screenY","href":"presets_fire_particle/FireParticleLayer/screenY.html","type":"property","overriddenDepth":0,"packageName":"dart_board_particles","enclosedBy":{"name":"FireParticleLayer","type":"class"}},{"name":"lighting_particle","qualifiedName":"lighting_particle","href":"presets_lighting_particle/presets_lighting_particle-library.html","type":"library","overriddenDepth":0,"packageName":"dart_board_particles"},{"name":"LightingParticle","qualifiedName":"lighting_particle.LightingParticle","href":"presets_lighting_particle/LightingParticle-class.html","type":"class","overriddenDepth":0,"packageName":"dart_board_particles","enclosedBy":{"name":"lighting_particle","type":"library"}},{"name":"LightingParticle","qualifiedName":"lighting_particle.LightingParticle.LightingParticle","href":"presets_lighting_particle/LightingParticle/LightingParticle.html","type":"constructor","overriddenDepth":0,"packageName":"dart_board_particles","enclosedBy":{"name":"LightingParticle","type":"class"}},{"name":"cw","qualifiedName":"lighting_particle.LightingParticle.cw","href":"presets_lighting_particle/LightingParticle/cw.html","type":"property","overriddenDepth":0,"packageName":"dart_board_particles","enclosedBy":{"name":"LightingParticle","type":"class"}},{"name":"r","qualifiedName":"lighting_particle.LightingParticle.r","href":"presets_lighting_particle/LightingParticle/r.html","type":"property","overriddenDepth":0,"packageName":"dart_board_particles","enclosedBy":{"name":"LightingParticle","type":"class"}},{"name":"r2","qualifiedName":"lighting_particle.LightingParticle.r2","href":"presets_lighting_particle/LightingParticle/r2.html","type":"property","overriddenDepth":0,"packageName":"dart_board_particles","enclosedBy":{"name":"LightingParticle","type":"class"}},{"name":"r3","qualifiedName":"lighting_particle.LightingParticle.r3","href":"presets_lighting_particle/LightingParticle/r3.html","type":"property","overriddenDepth":0,"packageName":"dart_board_particles","enclosedBy":{"name":"LightingParticle","type":"class"}},{"name":"s","qualifiedName":"lighting_particle.LightingParticle.s","href":"presets_lighting_particle/LightingParticle/s.html","type":"property","overriddenDepth":0,"packageName":"dart_board_particles","enclosedBy":{"name":"LightingParticle","type":"class"}},{"name":"step","qualifiedName":"lighting_particle.LightingParticle.step","href":"presets_lighting_particle/LightingParticle/step.html","type":"method","overriddenDepth":1,"packageName":"dart_board_particles","enclosedBy":{"name":"LightingParticle","type":"class"}},{"name":"t","qualifiedName":"lighting_particle.LightingParticle.t","href":"presets_lighting_particle/LightingParticle/t.html","type":"property","overriddenDepth":0,"packageName":"dart_board_particles","enclosedBy":{"name":"LightingParticle","type":"class"}},{"name":"x","qualifiedName":"lighting_particle.LightingParticle.x","href":"presets_lighting_particle/LightingParticle/x.html","type":"property","overriddenDepth":0,"packageName":"dart_board_particles","enclosedBy":{"name":"LightingParticle","type":"class"}},{"name":"y","qualifiedName":"lighting_particle.LightingParticle.y","href":"presets_lighting_particle/LightingParticle/y.html","type":"property","overriddenDepth":0,"packageName":"dart_board_particles","enclosedBy":{"name":"LightingParticle","type":"class"}},{"name":"LightingParticleLayer","qualifiedName":"lighting_particle.LightingParticleLayer","href":"presets_lighting_particle/LightingParticleLayer-class.html","type":"class","overriddenDepth":0,"packageName":"dart_board_particles","enclosedBy":{"name":"lighting_particle","type":"library"}},{"name":"LightingParticleLayer","qualifiedName":"lighting_particle.LightingParticleLayer.LightingParticleLayer","href":"presets_lighting_particle/LightingParticleLayer/LightingParticleLayer.html","type":"constructor","overriddenDepth":0,"packageName":"dart_board_particles","enclosedBy":{"name":"LightingParticleLayer","type":"class"}},{"name":"after","qualifiedName":"lighting_particle.LightingParticleLayer.after","href":"presets_lighting_particle/LightingParticleLayer/after.html","type":"method","overriddenDepth":1,"packageName":"dart_board_particles","enclosedBy":{"name":"LightingParticleLayer","type":"class"}},{"name":"before","qualifiedName":"lighting_particle.LightingParticleLayer.before","href":"presets_lighting_particle/LightingParticleLayer/before.html","type":"method","overriddenDepth":1,"packageName":"dart_board_particles","enclosedBy":{"name":"LightingParticleLayer","type":"class"}},{"name":"drawParticle","qualifiedName":"lighting_particle.LightingParticleLayer.drawParticle","href":"presets_lighting_particle/LightingParticleLayer/drawParticle.html","type":"method","overriddenDepth":1,"packageName":"dart_board_particles","enclosedBy":{"name":"LightingParticleLayer","type":"class"}},{"name":"isDead","qualifiedName":"lighting_particle.LightingParticleLayer.isDead","href":"presets_lighting_particle/LightingParticleLayer/isDead.html","type":"property","overriddenDepth":0,"packageName":"dart_board_particles","enclosedBy":{"name":"LightingParticleLayer","type":"class"}},{"name":"particles","qualifiedName":"lighting_particle.LightingParticleLayer.particles","href":"presets_lighting_particle/LightingParticleLayer/particles.html","type":"property","overriddenDepth":0,"packageName":"dart_board_particles","enclosedBy":{"name":"LightingParticleLayer","type":"class"}},{"name":"rainbow_particle","qualifiedName":"rainbow_particle","href":"presets_rainbow_particle/presets_rainbow_particle-library.html","type":"library","overriddenDepth":0,"packageName":"dart_board_particles"},{"name":"RainbowParticle","qualifiedName":"rainbow_particle.RainbowParticle","href":"presets_rainbow_particle/RainbowParticle-class.html","type":"class","overriddenDepth":0,"packageName":"dart_board_particles","enclosedBy":{"name":"rainbow_particle","type":"library"}},{"name":"RainbowParticle","qualifiedName":"rainbow_particle.RainbowParticle.RainbowParticle","href":"presets_rainbow_particle/RainbowParticle/RainbowParticle.html","type":"constructor","overriddenDepth":0,"packageName":"dart_board_particles","enclosedBy":{"name":"RainbowParticle","type":"class"}},{"name":"c","qualifiedName":"rainbow_particle.RainbowParticle.c","href":"presets_rainbow_particle/RainbowParticle/c.html","type":"property","overriddenDepth":0,"packageName":"dart_board_particles","enclosedBy":{"name":"RainbowParticle","type":"class"}},{"name":"s","qualifiedName":"rainbow_particle.RainbowParticle.s","href":"presets_rainbow_particle/RainbowParticle/s.html","type":"property","overriddenDepth":0,"packageName":"dart_board_particles","enclosedBy":{"name":"RainbowParticle","type":"class"}},{"name":"step","qualifiedName":"rainbow_particle.RainbowParticle.step","href":"presets_rainbow_particle/RainbowParticle/step.html","type":"method","overriddenDepth":1,"packageName":"dart_board_particles","enclosedBy":{"name":"RainbowParticle","type":"class"}},{"name":"t","qualifiedName":"rainbow_particle.RainbowParticle.t","href":"presets_rainbow_particle/RainbowParticle/t.html","type":"property","overriddenDepth":0,"packageName":"dart_board_particles","enclosedBy":{"name":"RainbowParticle","type":"class"}},{"name":"RainbowParticleLayer","qualifiedName":"rainbow_particle.RainbowParticleLayer","href":"presets_rainbow_particle/RainbowParticleLayer-class.html","type":"class","overriddenDepth":0,"packageName":"dart_board_particles","enclosedBy":{"name":"rainbow_particle","type":"library"}},{"name":"RainbowParticleLayer","qualifiedName":"rainbow_particle.RainbowParticleLayer.RainbowParticleLayer","href":"presets_rainbow_particle/RainbowParticleLayer/RainbowParticleLayer.html","type":"constructor","overriddenDepth":0,"packageName":"dart_board_particles","enclosedBy":{"name":"RainbowParticleLayer","type":"class"}},{"name":"after","qualifiedName":"rainbow_particle.RainbowParticleLayer.after","href":"presets_rainbow_particle/RainbowParticleLayer/after.html","type":"method","overriddenDepth":1,"packageName":"dart_board_particles","enclosedBy":{"name":"RainbowParticleLayer","type":"class"}},{"name":"before","qualifiedName":"rainbow_particle.RainbowParticleLayer.before","href":"presets_rainbow_particle/RainbowParticleLayer/before.html","type":"method","overriddenDepth":1,"packageName":"dart_board_particles","enclosedBy":{"name":"RainbowParticleLayer","type":"class"}},{"name":"drawParticle","qualifiedName":"rainbow_particle.RainbowParticleLayer.drawParticle","href":"presets_rainbow_particle/RainbowParticleLayer/drawParticle.html","type":"method","overriddenDepth":1,"packageName":"dart_board_particles","enclosedBy":{"name":"RainbowParticleLayer","type":"class"}},{"name":"isDead","qualifiedName":"rainbow_particle.RainbowParticleLayer.isDead","href":"presets_rainbow_particle/RainbowParticleLayer/isDead.html","type":"property","overriddenDepth":0,"packageName":"dart_board_particles","enclosedBy":{"name":"RainbowParticleLayer","type":"class"}},{"name":"lastScreenX","qualifiedName":"rainbow_particle.RainbowParticleLayer.lastScreenX","href":"presets_rainbow_particle/RainbowParticleLayer/lastScreenX.html","type":"property","overriddenDepth":0,"packageName":"dart_board_particles","enclosedBy":{"name":"RainbowParticleLayer","type":"class"}},{"name":"lastScreenY","qualifiedName":"rainbow_particle.RainbowParticleLayer.lastScreenY","href":"presets_rainbow_particle/RainbowParticleLayer/lastScreenY.html","type":"property","overriddenDepth":0,"packageName":"dart_board_particles","enclosedBy":{"name":"RainbowParticleLayer","type":"class"}},{"name":"particles","qualifiedName":"rainbow_particle.RainbowParticleLayer.particles","href":"presets_rainbow_particle/RainbowParticleLayer/particles.html","type":"property","overriddenDepth":0,"packageName":"dart_board_particles","enclosedBy":{"name":"RainbowParticleLayer","type":"class"}},{"name":"screenX","qualifiedName":"rainbow_particle.RainbowParticleLayer.screenX","href":"presets_rainbow_particle/RainbowParticleLayer/screenX.html","type":"property","overriddenDepth":0,"packageName":"dart_board_particles","enclosedBy":{"name":"RainbowParticleLayer","type":"class"}},{"name":"screenY","qualifiedName":"rainbow_particle.RainbowParticleLayer.screenY","href":"presets_rainbow_particle/RainbowParticleLayer/screenY.html","type":"property","overriddenDepth":0,"packageName":"dart_board_particles","enclosedBy":{"name":"RainbowParticleLayer","type":"class"}},{"name":"snow_feature","qualifiedName":"snow_feature","href":"features_snow_feature/features_snow_feature-library.html","type":"library","overriddenDepth":0,"packageName":"dart_board_particles"},{"name":"SnowFeature","qualifiedName":"snow_feature.SnowFeature","href":"features_snow_feature/SnowFeature-class.html","type":"class","overriddenDepth":0,"packageName":"dart_board_particles","enclosedBy":{"name":"snow_feature","type":"library"}},{"name":"SnowFeature","qualifiedName":"snow_feature.SnowFeature.SnowFeature","href":"features_snow_feature/SnowFeature/SnowFeature.html","type":"constructor","overriddenDepth":0,"packageName":"dart_board_particles","enclosedBy":{"name":"SnowFeature","type":"class"}},{"name":"appDecorations","qualifiedName":"snow_feature.SnowFeature.appDecorations","href":"features_snow_feature/SnowFeature/appDecorations.html","type":"property","overriddenDepth":0,"packageName":"dart_board_particles","enclosedBy":{"name":"SnowFeature","type":"class"}},{"name":"dependencies","qualifiedName":"snow_feature.SnowFeature.dependencies","href":"features_snow_feature/SnowFeature/dependencies.html","type":"property","overriddenDepth":0,"packageName":"dart_board_particles","enclosedBy":{"name":"SnowFeature","type":"class"}},{"name":"enabled","qualifiedName":"snow_feature.SnowFeature.enabled","href":"features_snow_feature/SnowFeature/enabled.html","type":"property","overriddenDepth":0,"packageName":"dart_board_particles","enclosedBy":{"name":"SnowFeature","type":"class"}},{"name":"implementationName","qualifiedName":"snow_feature.SnowFeature.implementationName","href":"features_snow_feature/SnowFeature/implementationName.html","type":"property","overriddenDepth":0,"packageName":"dart_board_particles","enclosedBy":{"name":"SnowFeature","type":"class"}},{"name":"namespace","qualifiedName":"snow_feature.SnowFeature.namespace","href":"features_snow_feature/SnowFeature/namespace.html","type":"property","overriddenDepth":0,"packageName":"dart_board_particles","enclosedBy":{"name":"SnowFeature","type":"class"}},{"name":"pageDecorationAllowList","qualifiedName":"snow_feature.SnowFeature.pageDecorationAllowList","href":"features_snow_feature/SnowFeature/pageDecorationAllowList.html","type":"property","overriddenDepth":0,"packageName":"dart_board_particles","enclosedBy":{"name":"SnowFeature","type":"class"}},{"name":"pageDecorationDenyList","qualifiedName":"snow_feature.SnowFeature.pageDecorationDenyList","href":"features_snow_feature/SnowFeature/pageDecorationDenyList.html","type":"property","overriddenDepth":0,"packageName":"dart_board_particles","enclosedBy":{"name":"SnowFeature","type":"class"}},{"name":"pageDecorations","qualifiedName":"snow_feature.SnowFeature.pageDecorations","href":"features_snow_feature/SnowFeature/pageDecorations.html","type":"property","overriddenDepth":0,"packageName":"dart_board_particles","enclosedBy":{"name":"SnowFeature","type":"class"}},{"name":"routes","qualifiedName":"snow_feature.SnowFeature.routes","href":"features_snow_feature/SnowFeature/routes.html","type":"property","overriddenDepth":0,"packageName":"dart_board_particles","enclosedBy":{"name":"SnowFeature","type":"class"}},{"name":"toString","qualifiedName":"snow_feature.SnowFeature.toString","href":"features_snow_feature/SnowFeature/toString.html","type":"method","overriddenDepth":1,"packageName":"dart_board_particles","enclosedBy":{"name":"SnowFeature","type":"class"}},{"name":"snow_particle","qualifiedName":"snow_particle","href":"presets_snow_particle/presets_snow_particle-library.html","type":"library","overriddenDepth":0,"packageName":"dart_board_particles"},{"name":"SnowParticle","qualifiedName":"snow_particle.SnowParticle","href":"presets_snow_particle/SnowParticle-class.html","type":"class","overriddenDepth":0,"packageName":"dart_board_particles","enclosedBy":{"name":"snow_particle","type":"library"}},{"name":"SnowParticle","qualifiedName":"snow_particle.SnowParticle.SnowParticle","href":"presets_snow_particle/SnowParticle/SnowParticle.html","type":"constructor","overriddenDepth":0,"packageName":"dart_board_particles","enclosedBy":{"name":"SnowParticle","type":"class"}},{"name":"c","qualifiedName":"snow_particle.SnowParticle.c","href":"presets_snow_particle/SnowParticle/c.html","type":"property","overriddenDepth":0,"packageName":"dart_board_particles","enclosedBy":{"name":"SnowParticle","type":"class"}},{"name":"oldX","qualifiedName":"snow_particle.SnowParticle.oldX","href":"presets_snow_particle/SnowParticle/oldX.html","type":"property","overriddenDepth":0,"packageName":"dart_board_particles","enclosedBy":{"name":"SnowParticle","type":"class"}},{"name":"oldY","qualifiedName":"snow_particle.SnowParticle.oldY","href":"presets_snow_particle/SnowParticle/oldY.html","type":"property","overriddenDepth":0,"packageName":"dart_board_particles","enclosedBy":{"name":"SnowParticle","type":"class"}},{"name":"r","qualifiedName":"snow_particle.SnowParticle.r","href":"presets_snow_particle/SnowParticle/r.html","type":"property","overriddenDepth":0,"packageName":"dart_board_particles","enclosedBy":{"name":"SnowParticle","type":"class"}},{"name":"r2","qualifiedName":"snow_particle.SnowParticle.r2","href":"presets_snow_particle/SnowParticle/r2.html","type":"property","overriddenDepth":0,"packageName":"dart_board_particles","enclosedBy":{"name":"SnowParticle","type":"class"}},{"name":"s","qualifiedName":"snow_particle.SnowParticle.s","href":"presets_snow_particle/SnowParticle/s.html","type":"property","overriddenDepth":0,"packageName":"dart_board_particles","enclosedBy":{"name":"SnowParticle","type":"class"}},{"name":"step","qualifiedName":"snow_particle.SnowParticle.step","href":"presets_snow_particle/SnowParticle/step.html","type":"method","overriddenDepth":1,"packageName":"dart_board_particles","enclosedBy":{"name":"SnowParticle","type":"class"}},{"name":"t","qualifiedName":"snow_particle.SnowParticle.t","href":"presets_snow_particle/SnowParticle/t.html","type":"property","overriddenDepth":0,"packageName":"dart_board_particles","enclosedBy":{"name":"SnowParticle","type":"class"}},{"name":"x","qualifiedName":"snow_particle.SnowParticle.x","href":"presets_snow_particle/SnowParticle/x.html","type":"property","overriddenDepth":0,"packageName":"dart_board_particles","enclosedBy":{"name":"SnowParticle","type":"class"}},{"name":"y","qualifiedName":"snow_particle.SnowParticle.y","href":"presets_snow_particle/SnowParticle/y.html","type":"property","overriddenDepth":0,"packageName":"dart_board_particles","enclosedBy":{"name":"SnowParticle","type":"class"}},{"name":"ys","qualifiedName":"snow_particle.SnowParticle.ys","href":"presets_snow_particle/SnowParticle/ys.html","type":"property","overriddenDepth":0,"packageName":"dart_board_particles","enclosedBy":{"name":"SnowParticle","type":"class"}},{"name":"SnowParticleLayer","qualifiedName":"snow_particle.SnowParticleLayer","href":"presets_snow_particle/SnowParticleLayer-class.html","type":"class","overriddenDepth":0,"packageName":"dart_board_particles","enclosedBy":{"name":"snow_particle","type":"library"}},{"name":"SnowParticleLayer","qualifiedName":"snow_particle.SnowParticleLayer.SnowParticleLayer","href":"presets_snow_particle/SnowParticleLayer/SnowParticleLayer.html","type":"constructor","overriddenDepth":0,"packageName":"dart_board_particles","enclosedBy":{"name":"SnowParticleLayer","type":"class"}},{"name":"after","qualifiedName":"snow_particle.SnowParticleLayer.after","href":"presets_snow_particle/SnowParticleLayer/after.html","type":"method","overriddenDepth":1,"packageName":"dart_board_particles","enclosedBy":{"name":"SnowParticleLayer","type":"class"}},{"name":"before","qualifiedName":"snow_particle.SnowParticleLayer.before","href":"presets_snow_particle/SnowParticleLayer/before.html","type":"method","overriddenDepth":1,"packageName":"dart_board_particles","enclosedBy":{"name":"SnowParticleLayer","type":"class"}},{"name":"drawParticle","qualifiedName":"snow_particle.SnowParticleLayer.drawParticle","href":"presets_snow_particle/SnowParticleLayer/drawParticle.html","type":"method","overriddenDepth":1,"packageName":"dart_board_particles","enclosedBy":{"name":"SnowParticleLayer","type":"class"}},{"name":"isDead","qualifiedName":"snow_particle.SnowParticleLayer.isDead","href":"presets_snow_particle/SnowParticleLayer/isDead.html","type":"property","overriddenDepth":0,"packageName":"dart_board_particles","enclosedBy":{"name":"SnowParticleLayer","type":"class"}},{"name":"needsAfter","qualifiedName":"snow_particle.SnowParticleLayer.needsAfter","href":"presets_snow_particle/SnowParticleLayer/needsAfter.html","type":"property","overriddenDepth":0,"packageName":"dart_board_particles","enclosedBy":{"name":"SnowParticleLayer","type":"class"}},{"name":"needsParticlePaint","qualifiedName":"snow_particle.SnowParticleLayer.needsParticlePaint","href":"presets_snow_particle/SnowParticleLayer/needsParticlePaint.html","type":"property","overriddenDepth":0,"packageName":"dart_board_particles","enclosedBy":{"name":"SnowParticleLayer","type":"class"}},{"name":"particles","qualifiedName":"snow_particle.SnowParticleLayer.particles","href":"presets_snow_particle/SnowParticleLayer/particles.html","type":"property","overriddenDepth":0,"packageName":"dart_board_particles","enclosedBy":{"name":"SnowParticleLayer","type":"class"}}]
